[
    {
        "%vlocity_namespace%__DomainObjectAPIName__c": "json",
        "%vlocity_namespace%__DomainObjectCreationOrder__c": 0,
        "%vlocity_namespace%__DomainObjectFieldAPIName__c": "Case",
        "%vlocity_namespace%__FilterGroup__c": 0,
        "%vlocity_namespace%__FilterOperator__c": "=",
        "%vlocity_namespace%__FilterValue__c": "caseId",
        "%vlocity_namespace%__InterfaceFieldAPIName__c": "Id",
        "%vlocity_namespace%__InterfaceObjectLookupOrder__c": 1,
        "%vlocity_namespace%__InterfaceObjectName__c": "Case",
        "%vlocity_namespace%__IsDisabled__c": false,
        "%vlocity_namespace%__IsRequiredForUpsert__c": false,
        "%vlocity_namespace%__MapId__c": "climsGetCaseWithContentDocuments38252021895124466",
        "%vlocity_namespace%__UpsertKey__c": false,
        "Name": "climsGetCaseWithContentDocuments",
        "VlocityDataPackType": "SObject",
        "VlocityRecordSObjectType": "%vlocity_namespace%__DRMapItem__c"
    },
    {
        "%vlocity_namespace%__DomainObjectAPIName__c": "json",
        "%vlocity_namespace%__DomainObjectCreationOrder__c": 0,
        "%vlocity_namespace%__DomainObjectFieldAPIName__c": "ContentDocumentLink",
        "%vlocity_namespace%__FilterGroup__c": 0,
        "%vlocity_namespace%__FilterOperator__c": "=",
        "%vlocity_namespace%__FilterValue__c": "Case:Id",
        "%vlocity_namespace%__InterfaceFieldAPIName__c": "LinkedEntityId",
        "%vlocity_namespace%__InterfaceObjectLookupOrder__c": 2,
        "%vlocity_namespace%__InterfaceObjectName__c": "ContentDocumentLink",
        "%vlocity_namespace%__IsDisabled__c": false,
        "%vlocity_namespace%__IsRequiredForUpsert__c": false,
        "%vlocity_namespace%__MapId__c": "climsGetCaseWithContentDocuments5499971237667465",
        "%vlocity_namespace%__UpsertKey__c": false,
        "Name": "climsGetCaseWithContentDocuments",
        "VlocityDataPackType": "SObject",
        "VlocityRecordSObjectType": "%vlocity_namespace%__DRMapItem__c"
    },
    {
        "%vlocity_namespace%__DomainObjectAPIName__c": "json",
        "%vlocity_namespace%__DomainObjectCreationOrder__c": 0,
        "%vlocity_namespace%__DomainObjectFieldAPIName__c": "ContentVersion",
        "%vlocity_namespace%__FilterGroup__c": 0,
        "%vlocity_namespace%__FilterOperator__c": "=",
        "%vlocity_namespace%__FilterValue__c": "ContentDocumentLink:ContentDocumentId",
        "%vlocity_namespace%__InterfaceFieldAPIName__c": "ContentDocumentId",
        "%vlocity_namespace%__InterfaceObjectLookupOrder__c": 3,
        "%vlocity_namespace%__InterfaceObjectName__c": "ContentVersion",
        "%vlocity_namespace%__IsDisabled__c": false,
        "%vlocity_namespace%__IsRequiredForUpsert__c": false,
        "%vlocity_namespace%__MapId__c": "climsGetCaseWithContentDocuments6586352653489167",
        "%vlocity_namespace%__UpsertKey__c": false,
        "Name": "climsGetCaseWithContentDocuments",
        "VlocityDataPackType": "SObject",
        "VlocityRecordSObjectType": "%vlocity_namespace%__DRMapItem__c"
    },
    {
        "%vlocity_namespace%__DomainObjectAPIName__c": "json",
        "%vlocity_namespace%__DomainObjectCreationOrder__c": 0,
        "%vlocity_namespace%__DomainObjectFieldAPIName__c": "Member",
        "%vlocity_namespace%__FilterGroup__c": 0,
        "%vlocity_namespace%__FilterOperator__c": "=",
        "%vlocity_namespace%__FilterValue__c": "Case:ContactId",
        "%vlocity_namespace%__InterfaceFieldAPIName__c": "Id",
        "%vlocity_namespace%__InterfaceObjectLookupOrder__c": 4,
        "%vlocity_namespace%__InterfaceObjectName__c": "Contact",
        "%vlocity_namespace%__IsDisabled__c": false,
        "%vlocity_namespace%__IsRequiredForUpsert__c": false,
        "%vlocity_namespace%__MapId__c": "climsGetCaseWithContentDocumentsCustom7164",
        "%vlocity_namespace%__UpsertKey__c": false,
        "Name": "climsGetCaseWithContentDocuments",
        "VlocityDataPackType": "SObject",
        "VlocityRecordSObjectType": "%vlocity_namespace%__DRMapItem__c"
    },
    {
        "%vlocity_namespace%__DomainObjectAPIName__c": "Formula",
        "%vlocity_namespace%__DomainObjectCreationOrder__c": 0,
        "%vlocity_namespace%__DomainObjectFieldAPIName__c": "Formula",
        "%vlocity_namespace%__FormulaOrder__c": 1,
        "%vlocity_namespace%__FormulaResultPath__c": "inboxExternalId",
        "%vlocity_namespace%__Formula__c": "CONCAT(\"IMS__\", Case:Contact_Us_Topic__c, \"__\",Case:Contact_Us_Subtopic__c)",
        "%vlocity_namespace%__IsDisabled__c": false,
        "%vlocity_namespace%__IsRequiredForUpsert__c": false,
        "%vlocity_namespace%__MapId__c": "climsGetCaseWithContentDocuments03835327168319025",
        "%vlocity_namespace%__UpsertKey__c": false,
        "Name": "climsGetCaseWithContentDocuments",
        "VlocityDataPackType": "SObject",
        "VlocityRecordSObjectType": "%vlocity_namespace%__DRMapItem__c"
    },
    {
        "%vlocity_namespace%__DomainObjectAPIName__c": "Formula",
        "%vlocity_namespace%__DomainObjectCreationOrder__c": 0,
        "%vlocity_namespace%__DomainObjectFieldAPIName__c": "Formula",
        "%vlocity_namespace%__FormulaOrder__c": 2,
        "%vlocity_namespace%__FormulaResultPath__c": "VersionDocs",
        "%vlocity_namespace%__Formula__c": "ContentVersion:Id",
        "%vlocity_namespace%__IsDisabled__c": false,
        "%vlocity_namespace%__IsRequiredForUpsert__c": false,
        "%vlocity_namespace%__MapId__c": "climsGetCaseWithContentDocuments8839497189484959",
        "%vlocity_namespace%__UpsertKey__c": false,
        "Name": "climsGetCaseWithContentDocuments",
        "VlocityDataPackType": "SObject",
        "VlocityRecordSObjectType": "%vlocity_namespace%__DRMapItem__c"
    },
    {
        "%vlocity_namespace%__DomainObjectAPIName__c": "Formula",
        "%vlocity_namespace%__DomainObjectCreationOrder__c": 0,
        "%vlocity_namespace%__DomainObjectFieldAPIName__c": "Formula",
        "%vlocity_namespace%__FormulaOrder__c": 3,
        "%vlocity_namespace%__FormulaResultPath__c": "isAttachment",
        "%vlocity_namespace%__Formula__c": "ISBLANK(ContentVersions)",
        "%vlocity_namespace%__IsDisabled__c": false,
        "%vlocity_namespace%__IsRequiredForUpsert__c": false,
        "%vlocity_namespace%__MapId__c": "climsGetCaseWithContentDocuments26763520132243235",
        "%vlocity_namespace%__UpsertKey__c": false,
        "Name": "climsGetCaseWithContentDocuments",
        "VlocityDataPackType": "SObject",
        "VlocityRecordSObjectType": "%vlocity_namespace%__DRMapItem__c"
    },
    {
        "%vlocity_namespace%__DomainObjectAPIName__c": "json",
        "%vlocity_namespace%__DomainObjectCreationOrder__c": 1,
        "%vlocity_namespace%__DomainObjectFieldAPIName__c": "Case:caseAccountId",
        "%vlocity_namespace%__InterfaceFieldAPIName__c": "Case:AccountId",
        "%vlocity_namespace%__IsDisabled__c": false,
        "%vlocity_namespace%__IsRequiredForUpsert__c": false,
        "%vlocity_namespace%__MapId__c": "climsGetCaseWithContentDocuments7982959903257705",
        "%vlocity_namespace%__UpsertKey__c": false,
        "Name": "climsGetCaseWithContentDocuments",
        "VlocityDataPackType": "SObject",
        "VlocityRecordSObjectType": "%vlocity_namespace%__DRMapItem__c"
    },
    {
        "%vlocity_namespace%__DomainObjectAPIName__c": "json",
        "%vlocity_namespace%__DomainObjectCreationOrder__c": 1,
        "%vlocity_namespace%__DomainObjectFieldAPIName__c": "Case:caseContactEmail",
        "%vlocity_namespace%__InterfaceFieldAPIName__c": "Case:ContactEmail",
        "%vlocity_namespace%__IsDisabled__c": false,
        "%vlocity_namespace%__IsRequiredForUpsert__c": false,
        "%vlocity_namespace%__MapId__c": "climsGetCaseWithContentDocuments43876578694363966",
        "%vlocity_namespace%__UpsertKey__c": false,
        "Name": "climsGetCaseWithContentDocuments",
        "VlocityDataPackType": "SObject",
        "VlocityRecordSObjectType": "%vlocity_namespace%__DRMapItem__c"
    },
    {
        "%vlocity_namespace%__DomainObjectAPIName__c": "json",
        "%vlocity_namespace%__DomainObjectCreationOrder__c": 1,
        "%vlocity_namespace%__DomainObjectFieldAPIName__c": "Case:caseContactId",
        "%vlocity_namespace%__InterfaceFieldAPIName__c": "Case:ContactId",
        "%vlocity_namespace%__IsDisabled__c": false,
        "%vlocity_namespace%__IsRequiredForUpsert__c": false,
        "%vlocity_namespace%__MapId__c": "climsGetCaseWithContentDocuments5485096203131714",
        "%vlocity_namespace%__UpsertKey__c": false,
        "Name": "climsGetCaseWithContentDocuments",
        "VlocityDataPackType": "SObject",
        "VlocityRecordSObjectType": "%vlocity_namespace%__DRMapItem__c"
    },
    {
        "%vlocity_namespace%__DomainObjectAPIName__c": "json",
        "%vlocity_namespace%__DomainObjectCreationOrder__c": 1,
        "%vlocity_namespace%__DomainObjectFieldAPIName__c": "Case:caseId",
        "%vlocity_namespace%__InterfaceFieldAPIName__c": "CaseId",
        "%vlocity_namespace%__IsDisabled__c": false,
        "%vlocity_namespace%__IsRequiredForUpsert__c": false,
        "%vlocity_namespace%__MapId__c": "climsGetCaseWithContentDocuments5796626821778561",
        "%vlocity_namespace%__UpsertKey__c": false,
        "Name": "climsGetCaseWithContentDocuments",
        "VlocityDataPackType": "SObject",
        "VlocityRecordSObjectType": "%vlocity_namespace%__DRMapItem__c"
    },
    {
        "%vlocity_namespace%__DomainObjectAPIName__c": "json",
        "%vlocity_namespace%__DomainObjectCreationOrder__c": 1,
        "%vlocity_namespace%__DomainObjectFieldAPIName__c": "Case:caseNumber",
        "%vlocity_namespace%__InterfaceFieldAPIName__c": "Case:CaseNumber",
        "%vlocity_namespace%__IsDisabled__c": false,
        "%vlocity_namespace%__IsRequiredForUpsert__c": false,
        "%vlocity_namespace%__MapId__c": "climsGetCaseWithContentDocumentsCustom9304",
        "%vlocity_namespace%__UpsertKey__c": false,
        "Name": "climsGetCaseWithContentDocuments",
        "VlocityDataPackType": "SObject",
        "VlocityRecordSObjectType": "%vlocity_namespace%__DRMapItem__c"
    },
    {
        "%vlocity_namespace%__DomainObjectAPIName__c": "json",
        "%vlocity_namespace%__DomainObjectCreationOrder__c": 1,
        "%vlocity_namespace%__DomainObjectFieldAPIName__c": "Case:caseSubTopic",
        "%vlocity_namespace%__InterfaceFieldAPIName__c": "Case:Contact_Us_Subtopic__c",
        "%vlocity_namespace%__IsDisabled__c": false,
        "%vlocity_namespace%__IsRequiredForUpsert__c": false,
        "%vlocity_namespace%__MapId__c": "climsGetCaseWithContentDocuments4399988113917255",
        "%vlocity_namespace%__UpsertKey__c": false,
        "Name": "climsGetCaseWithContentDocuments",
        "VlocityDataPackType": "SObject",
        "VlocityRecordSObjectType": "%vlocity_namespace%__DRMapItem__c"
    },
    {
        "%vlocity_namespace%__DomainObjectAPIName__c": "json",
        "%vlocity_namespace%__DomainObjectCreationOrder__c": 1,
        "%vlocity_namespace%__DomainObjectFieldAPIName__c": "Case:caseSupplierEmail",
        "%vlocity_namespace%__InterfaceFieldAPIName__c": "Case:SuppliedEmail",
        "%vlocity_namespace%__IsDisabled__c": false,
        "%vlocity_namespace%__IsRequiredForUpsert__c": false,
        "%vlocity_namespace%__MapId__c": "climsGetCaseWithContentDocuments3366868382184285",
        "%vlocity_namespace%__UpsertKey__c": false,
        "Name": "climsGetCaseWithContentDocuments",
        "VlocityDataPackType": "SObject",
        "VlocityRecordSObjectType": "%vlocity_namespace%__DRMapItem__c"
    },
    {
        "%vlocity_namespace%__DomainObjectAPIName__c": "json",
        "%vlocity_namespace%__DomainObjectCreationOrder__c": 1,
        "%vlocity_namespace%__DomainObjectFieldAPIName__c": "Case:caseTopic",
        "%vlocity_namespace%__InterfaceFieldAPIName__c": "Case:Contact_Us_Topic__c",
        "%vlocity_namespace%__IsDisabled__c": false,
        "%vlocity_namespace%__IsRequiredForUpsert__c": false,
        "%vlocity_namespace%__MapId__c": "climsGetCaseWithContentDocuments7539161731405917",
        "%vlocity_namespace%__UpsertKey__c": false,
        "Name": "climsGetCaseWithContentDocuments",
        "VlocityDataPackType": "SObject",
        "VlocityRecordSObjectType": "%vlocity_namespace%__DRMapItem__c"
    },
    {
        "%vlocity_namespace%__DomainObjectAPIName__c": "json",
        "%vlocity_namespace%__DomainObjectCreationOrder__c": 1,
        "%vlocity_namespace%__DomainObjectFieldAPIName__c": "Case:inboxExternalId",
        "%vlocity_namespace%__InterfaceFieldAPIName__c": "inboxExternalId",
        "%vlocity_namespace%__IsDisabled__c": false,
        "%vlocity_namespace%__IsRequiredForUpsert__c": false,
        "%vlocity_namespace%__MapId__c": "climsGetCaseWithContentDocuments5128842771650088",
        "%vlocity_namespace%__UpsertKey__c": false,
        "Name": "climsGetCaseWithContentDocuments",
        "VlocityDataPackType": "SObject",
        "VlocityRecordSObjectType": "%vlocity_namespace%__DRMapItem__c"
    },
    {
        "%vlocity_namespace%__DomainObjectAPIName__c": "json",
        "%vlocity_namespace%__DomainObjectCreationOrder__c": 1,
        "%vlocity_namespace%__DomainObjectFieldAPIName__c": "Case:isAttachment",
        "%vlocity_namespace%__InterfaceFieldAPIName__c": "isAttachment",
        "%vlocity_namespace%__IsDisabled__c": false,
        "%vlocity_namespace%__IsRequiredForUpsert__c": false,
        "%vlocity_namespace%__MapId__c": "climsGetCaseWithContentDocuments6384468160444559",
        "%vlocity_namespace%__UpsertKey__c": false,
        "Name": "climsGetCaseWithContentDocuments",
        "VlocityDataPackType": "SObject",
        "VlocityRecordSObjectType": "%vlocity_namespace%__DRMapItem__c"
    },
    {
        "%vlocity_namespace%__DomainObjectAPIName__c": "json",
        "%vlocity_namespace%__DomainObjectCreationOrder__c": 1,
        "%vlocity_namespace%__DomainObjectFieldAPIName__c": "ContentVersions",
        "%vlocity_namespace%__InterfaceFieldAPIName__c": "VersionDocs",
        "%vlocity_namespace%__IsDisabled__c": false,
        "%vlocity_namespace%__IsRequiredForUpsert__c": false,
        "%vlocity_namespace%__MapId__c": "climsGetCaseWithContentDocuments8018265876338795",
        "%vlocity_namespace%__UpsertKey__c": false,
        "Name": "climsGetCaseWithContentDocuments",
        "VlocityDataPackType": "SObject",
        "VlocityRecordSObjectType": "%vlocity_namespace%__DRMapItem__c"
    },
    {
        "%vlocity_namespace%__DomainObjectAPIName__c": "json",
        "%vlocity_namespace%__DomainObjectCreationOrder__c": 1,
        "%vlocity_namespace%__DomainObjectFieldAPIName__c": "Member:firstName",
        "%vlocity_namespace%__InterfaceFieldAPIName__c": "Member:FirstName",
        "%vlocity_namespace%__IsDisabled__c": false,
        "%vlocity_namespace%__IsRequiredForUpsert__c": false,
        "%vlocity_namespace%__MapId__c": "climsGetCaseWithContentDocumentsCustom2182",
        "%vlocity_namespace%__UpsertKey__c": false,
        "Name": "climsGetCaseWithContentDocuments",
        "VlocityDataPackType": "SObject",
        "VlocityRecordSObjectType": "%vlocity_namespace%__DRMapItem__c"
    },
    {
        "%vlocity_namespace%__DomainObjectAPIName__c": "json",
        "%vlocity_namespace%__DomainObjectCreationOrder__c": 1,
        "%vlocity_namespace%__DomainObjectFieldAPIName__c": "Member:lastName",
        "%vlocity_namespace%__InterfaceFieldAPIName__c": "Member:LastName",
        "%vlocity_namespace%__IsDisabled__c": false,
        "%vlocity_namespace%__IsRequiredForUpsert__c": false,
        "%vlocity_namespace%__MapId__c": "climsGetCaseWithContentDocumentsCustom1318",
        "%vlocity_namespace%__UpsertKey__c": false,
        "Name": "climsGetCaseWithContentDocuments",
        "VlocityDataPackType": "SObject",
        "VlocityRecordSObjectType": "%vlocity_namespace%__DRMapItem__c"
    },
    {
        "%vlocity_namespace%__DomainObjectAPIName__c": "json",
        "%vlocity_namespace%__DomainObjectCreationOrder__c": 1,
        "%vlocity_namespace%__DomainObjectFieldAPIName__c": "Member:memberEmail",
        "%vlocity_namespace%__InterfaceFieldAPIName__c": "Member:Email",
        "%vlocity_namespace%__IsDisabled__c": false,
        "%vlocity_namespace%__IsRequiredForUpsert__c": false,
        "%vlocity_namespace%__MapId__c": "climsGetCaseWithContentDocumentsCustom7904",
        "%vlocity_namespace%__UpsertKey__c": false,
        "Name": "climsGetCaseWithContentDocuments",
        "VlocityDataPackType": "SObject",
        "VlocityRecordSObjectType": "%vlocity_namespace%__DRMapItem__c"
    },
    {
        "%vlocity_namespace%__DomainObjectAPIName__c": "json",
        "%vlocity_namespace%__DomainObjectCreationOrder__c": 1,
        "%vlocity_namespace%__DomainObjectFieldAPIName__c": "Member:name",
        "%vlocity_namespace%__InterfaceFieldAPIName__c": "Member:Name",
        "%vlocity_namespace%__IsDisabled__c": false,
        "%vlocity_namespace%__IsRequiredForUpsert__c": false,
        "%vlocity_namespace%__MapId__c": "climsGetCaseWithContentDocumentsCustom4389",
        "%vlocity_namespace%__UpsertKey__c": false,
        "Name": "climsGetCaseWithContentDocuments",
        "VlocityDataPackType": "SObject",
        "VlocityRecordSObjectType": "%vlocity_namespace%__DRMapItem__c"
    }
]